acddaun/__init__.py
acddaun/acddaun.py
acddaun-2.6.dist-info/METADATA
acddaun-2.6.dist-info/WHEEL
acddaun-2.6.dist-info/top_level.txt
acddaun-2.6.dist-info/RECORD
