Metadata-Version: 2.1
Name: acddaun
Version: 2.6
Summary: acddaun
Home-page: UNKNOWN
Author: Sasibacka
Author-email: sergeycikkatkovcik@gmail.com
License: UNKNOWN
Platform: UNKNOWN
Requires-Dist: pyautogui
